BigQuery_DatasetManager-0.1.6.dist-info/METADATA
BigQuery_DatasetManager-0.1.6.dist-info/RECORD
BigQuery_DatasetManager-0.1.6.dist-info/WHEEL
BigQuery_DatasetManager-0.1.6.dist-info/entry_points.txt
BigQuery_DatasetManager-0.1.6.dist-info/top_level.txt
bqdm/__init__.py
bqdm/cli.py
bqdm/message.py
bqdm/util.py
bqdm/action/__init__.py
bqdm/action/dataset.py
bqdm/action/table.py
bqdm/model/__init__.py
bqdm/model/dataset.py
bqdm/model/schema.py
bqdm/model/table.py
tests/__init__.py
tests/conftest.py
tests/test_util.py
tests/util.py
tests/action/__init__.py
tests/action/test_dataset.py
tests/action/test_table.py
tests/model/__init__.py
tests/model/test_dataset.py
tests/model/test_schema.py
tests/model/test_table.py
