Metadata-Version: 2.1
Name: BigQuery-DatasetManager
Version: 0.1.6
Summary: BigQuery-DatasetManager is a simple file-based CLI management tool for BigQuery Datasets.
Home-page: https://github.com/laughingman7743/BigQuery-DatasetManager/
Author: laughingman7743
Author-email: laughingman7743@gmail.com
License: MIT License
Platform: UNKNOWN
Classifier: Development Status :: 4 - Beta
Classifier: Intended Audience :: System Administrators
Classifier: License :: OSI Approved :: MIT License
Classifier: Operating System :: OS Independent
Classifier: Topic :: Database
Classifier: Programming Language :: Python :: 2
Classifier: Programming Language :: Python :: 2.7
Classifier: Programming Language :: Python :: 3
Classifier: Programming Language :: Python :: 3.4
Classifier: Programming Language :: Python :: 3.5
Classifier: Programming Language :: Python :: 3.6
Requires-Dist: future
Requires-Dist: pytz
Requires-Dist: click (>=6.0)
Requires-Dist: PyYAML (>=3.12)
Requires-Dist: google-cloud-bigquery (==1.1.0)
Requires-Dist: google-api-python-client (>=1.7.0)
Requires-Dist: python-dateutil (>=2.7.0)
Requires-Dist: enum34; python_version <= "3.3"
